{
    "pipes": [],
    "interfaces": [],
    "injectables": [],
    "guards": [],
    "interceptors": [],
    "classes": [],
    "directives": [],
    "components": [],
    "modules": [],
    "miscellaneous": {
        "variables": [
            {
                "name": "Checked",
                "ctype": "miscellaneous",
                "subtype": "variable",
                "file": "projects/solias-components/src/stories/form-controls/checkbox.stories.ts",
                "deprecated": false,
                "deprecationMessage": "",
                "type": "Story",
                "defaultValue": "{\r\n  render: (args) => ({\r\n    props: args,\r\n    template: `<input soliasCheckbox type=\"checkbox\" checked/>`,\r\n  }),\r\n}"
            },
            {
                "name": "Checked",
                "ctype": "miscellaneous",
                "subtype": "variable",
                "file": "projects/solias-components/src/stories/form-controls/radio.stories.ts",
                "deprecated": false,
                "deprecationMessage": "",
                "type": "Story",
                "defaultValue": "{\r\n  render: (args) => ({\r\n    props: args,\r\n    template: `<input soliasRadio type=\"radio\" checked />`,\r\n  }),\r\n}"
            },
            {
                "name": "defaultState",
                "ctype": "miscellaneous",
                "subtype": "variable",
                "file": "projects/solias-components/src/stories/form-controls/checkbox.stories.ts",
                "deprecated": false,
                "deprecationMessage": "",
                "type": "Story",
                "defaultValue": "{\r\n  render: (args) => ({\r\n    props: args,\r\n    template: `<input soliasCheckbox type=\"checkbox\" />`,\r\n  }),\r\n}"
            },
            {
                "name": "defaultState",
                "ctype": "miscellaneous",
                "subtype": "variable",
                "file": "projects/solias-components/src/stories/form-controls/radio.stories.ts",
                "deprecated": false,
                "deprecationMessage": "",
                "type": "Story",
                "defaultValue": "{\r\n  render: (args) => ({\r\n    props: args,\r\n    template: `<input soliasRadio type=\"radio\" />`,\r\n  }),\r\n}"
            },
            {
                "name": "defaultState",
                "ctype": "miscellaneous",
                "subtype": "variable",
                "file": "projects/solias-components/src/stories/form-controls/range.stories.ts",
                "deprecated": false,
                "deprecationMessage": "",
                "type": "Story",
                "defaultValue": "{\r\n  render: (args) => ({\r\n    props: args,\r\n    template: `<input soliasRange type=\"range\" />`,\r\n  }),\r\n}"
            },
            {
                "name": "Disabled",
                "ctype": "miscellaneous",
                "subtype": "variable",
                "file": "projects/solias-components/src/stories/buttons/button.stories.ts",
                "deprecated": false,
                "deprecationMessage": "",
                "type": "Story",
                "defaultValue": "{\n  args: {\n    variant: 'primary',\n    disabled: true,\n  },\n}"
            },
            {
                "name": "DisabledChecked",
                "ctype": "miscellaneous",
                "subtype": "variable",
                "file": "projects/solias-components/src/stories/form-controls/checkbox.stories.ts",
                "deprecated": false,
                "deprecationMessage": "",
                "type": "Story",
                "defaultValue": "{\r\n  render: (args) => ({\r\n    props: args,\r\n    template: `<input soliasCheckbox type=\"checkbox\" [disabled]=\"true\" />`,\r\n  }),\r\n}"
            },
            {
                "name": "DisabledChecked",
                "ctype": "miscellaneous",
                "subtype": "variable",
                "file": "projects/solias-components/src/stories/form-controls/radio.stories.ts",
                "deprecated": false,
                "deprecationMessage": "",
                "type": "Story",
                "defaultValue": "{\r\n  render: (args) => ({\r\n    props: args,\r\n    template: `<input soliasRadio type=\"radio\" [disabled]=\"true\" />`,\r\n  }),\r\n}"
            },
            {
                "name": "disabledState",
                "ctype": "miscellaneous",
                "subtype": "variable",
                "file": "projects/solias-components/src/stories/form-controls/range.stories.ts",
                "deprecated": false,
                "deprecationMessage": "",
                "type": "Story",
                "defaultValue": "{\r\n  render: (args) => ({\r\n    props: args,\r\n    template: `<input soliasRange type=\"range\" [disabled]=\"true\" />`,\r\n  }),\r\n}"
            },
            {
                "name": "DisabledUnchecked",
                "ctype": "miscellaneous",
                "subtype": "variable",
                "file": "projects/solias-components/src/stories/form-controls/checkbox.stories.ts",
                "deprecated": false,
                "deprecationMessage": "",
                "type": "Story",
                "defaultValue": "{\r\n  render: (args) => ({\r\n    props: args,\r\n    template: `<input soliasCheckbox type=\"checkbox\" [disabled]=\"true\" checked />`,\r\n  }),\r\n}"
            },
            {
                "name": "DisabledUnchecked",
                "ctype": "miscellaneous",
                "subtype": "variable",
                "file": "projects/solias-components/src/stories/form-controls/radio.stories.ts",
                "deprecated": false,
                "deprecationMessage": "",
                "type": "Story",
                "defaultValue": "{\r\n  render: (args) => ({\r\n    props: args,\r\n    template: `<input soliasRadio type=\"radio\" [disabled]=\"true\" checked />`,\r\n  }),\r\n}"
            },
            {
                "name": "Error",
                "ctype": "miscellaneous",
                "subtype": "variable",
                "file": "projects/solias-components/src/stories/buttons/button.stories.ts",
                "deprecated": false,
                "deprecationMessage": "",
                "type": "Story",
                "defaultValue": "{\n  args: {\n    variant: 'error',\n  },\n}"
            },
            {
                "name": "inputDisabledState",
                "ctype": "miscellaneous",
                "subtype": "variable",
                "file": "projects/solias-components/src/stories/form-controls/input.stories.ts",
                "deprecated": false,
                "deprecationMessage": "",
                "type": "Story",
                "defaultValue": "{\r\n  render: (args) => ({\r\n    props: args,\r\n    template: `<input soliasInput type=\"text\" [disabled]=\"true\" [value]=\"'Disabled value'\" />`,\r\n  }),\r\n}"
            },
            {
                "name": "inputInvalidState",
                "ctype": "miscellaneous",
                "subtype": "variable",
                "file": "projects/solias-components/src/stories/form-controls/input.stories.ts",
                "deprecated": false,
                "deprecationMessage": "",
                "type": "Story",
                "defaultValue": "{\r\n  render: (args) => ({\r\n    props: args,\r\n    template: `<input soliasInput type=\"text\" [validity]=\"'invalid'\" [value]=\"'Invalid value'\" />`,\r\n  }),\r\n}"
            },
            {
                "name": "inputReadonlyState",
                "ctype": "miscellaneous",
                "subtype": "variable",
                "file": "projects/solias-components/src/stories/form-controls/input.stories.ts",
                "deprecated": false,
                "deprecationMessage": "",
                "type": "Story",
                "defaultValue": "{\r\n  render: (args) => ({\r\n    props: args,\r\n    template: `<input soliasInput type=\"text\" [readOnly]=\"true\" [value]=\"'Readonly value'\" />`,\r\n  }),\r\n}"
            },
            {
                "name": "inputValidState",
                "ctype": "miscellaneous",
                "subtype": "variable",
                "file": "projects/solias-components/src/stories/form-controls/input.stories.ts",
                "deprecated": false,
                "deprecationMessage": "",
                "type": "Story",
                "defaultValue": "{\r\n  render: (args) => ({\r\n    props: args,\r\n    template: `<input soliasInput type=\"text\" [validity]=\"'valid'\" [value]=\"'Valid value'\" />`,\r\n  }),\r\n}"
            },
            {
                "name": "Large",
                "ctype": "miscellaneous",
                "subtype": "variable",
                "file": "projects/solias-components/src/stories/buttons/button.stories.ts",
                "deprecated": false,
                "deprecationMessage": "",
                "type": "Story",
                "defaultValue": "{\n  args: {\n    variant: 'primary',\n    size: 'large',\n  },\n}"
            },
            {
                "name": "meta",
                "ctype": "miscellaneous",
                "subtype": "variable",
                "file": "projects/solias-components/src/stories/buttons/button.stories.ts",
                "deprecated": false,
                "deprecationMessage": "",
                "type": "Meta<SoliasButtonDirective>",
                "defaultValue": "{\n  title: 'Buttons/Button',\n  component: SoliasButtonDirective,\n  tags: ['autodocs'],\n  argTypes: {\n    variant: {\n      control: 'select',\n      options: ['primary', 'secondary', 'tertiary', 'success', 'error'],\n      table: { defaultValue: { summary: 'primary' } },\n    },\n    size: {\n      control: 'select',\n      options: ['small', 'medium', 'large'],\n      table: { defaultValue: { summary: 'medium' } },\n    },\n    outlined: {\n      control: 'boolean',\n      table: { defaultValue: { summary: 'false' } },\n    },\n    disabled: {\n      control: 'boolean',\n      table: { defaultValue: { summary: 'false' } },\n    },\n  },\n  render: (args) => ({\n    props: args,\n    template: `<button soliasButton [variant]=\"variant\" [size]=\"size\" [outlined]=\"outlined\" [disabled]=\"disabled\">Button</button>`,\n  }),\n}"
            },
            {
                "name": "meta",
                "ctype": "miscellaneous",
                "subtype": "variable",
                "file": "projects/solias-components/src/stories/form-controls/checkbox.stories.ts",
                "deprecated": false,
                "deprecationMessage": "",
                "type": "Meta<SoliasCheckboxDirective>",
                "defaultValue": "{\r\n  title: 'Form Controls/Checkbox',\r\n  component: SoliasCheckboxDirective,\r\n  tags: ['autodocs']\r\n}"
            },
            {
                "name": "meta",
                "ctype": "miscellaneous",
                "subtype": "variable",
                "file": "projects/solias-components/src/stories/form-controls/input.stories.ts",
                "deprecated": false,
                "deprecationMessage": "",
                "type": "Meta<SoliasInputDirective>",
                "defaultValue": "{\r\n  component: SoliasInputDirective,\r\n  title: 'Form Controls/Inputs',\r\n  tags: ['autodocs'],\r\n}"
            },
            {
                "name": "meta",
                "ctype": "miscellaneous",
                "subtype": "variable",
                "file": "projects/solias-components/src/stories/form-controls/radio.stories.ts",
                "deprecated": false,
                "deprecationMessage": "",
                "type": "Meta<SoliasRadioDirective>",
                "defaultValue": "{\r\n  title: 'Form Controls/Radio',\r\n  component: SoliasRadioDirective,\r\n  tags: ['autodocs'],\r\n}"
            },
            {
                "name": "meta",
                "ctype": "miscellaneous",
                "subtype": "variable",
                "file": "projects/solias-components/src/stories/form-controls/range.stories.ts",
                "deprecated": false,
                "deprecationMessage": "",
                "type": "Meta<SoliasRangeDirective>",
                "defaultValue": "{\r\n  title: 'Form Controls/Range',\r\n  component: SoliasRangeDirective,\r\n  tags: ['autodocs']\r\n}"
            },
            {
                "name": "meta",
                "ctype": "miscellaneous",
                "subtype": "variable",
                "file": "projects/solias-components/src/stories/form-controls/select.stories.ts",
                "deprecated": false,
                "deprecationMessage": "",
                "type": "Meta<SoliasSelectDirective>",
                "defaultValue": "{\r\n  component: SoliasSelectDirective,\r\n  title: 'Form Controls/Select',\r\n  tags: ['autodocs'],\r\n}"
            },
            {
                "name": "meta",
                "ctype": "miscellaneous",
                "subtype": "variable",
                "file": "projects/solias-components/src/stories/form-controls/textarea.stories.ts",
                "deprecated": false,
                "deprecationMessage": "",
                "type": "Meta<SoliasTextareaDirective>",
                "defaultValue": "{\r\n  component: SoliasTextareaDirective,\r\n  title: 'Form Controls/Textarea',\r\n  tags: ['autodocs'],\r\n}"
            },
            {
                "name": "numberInput",
                "ctype": "miscellaneous",
                "subtype": "variable",
                "file": "projects/solias-components/src/stories/form-controls/input.stories.ts",
                "deprecated": false,
                "deprecationMessage": "",
                "type": "Story",
                "defaultValue": "{\r\n  render: (args) => ({\r\n    props: args,\r\n    template: `<input soliasInput type=\"number\" placeholder=\"Enter number\" />`,\r\n  }),\r\n}"
            },
            {
                "name": "Outlined",
                "ctype": "miscellaneous",
                "subtype": "variable",
                "file": "projects/solias-components/src/stories/buttons/button.stories.ts",
                "deprecated": false,
                "deprecationMessage": "",
                "type": "Story",
                "defaultValue": "{\n  args: {\n    variant: 'primary',\n    outlined: true,\n  },\n}"
            },
            {
                "name": "passwordInput",
                "ctype": "miscellaneous",
                "subtype": "variable",
                "file": "projects/solias-components/src/stories/form-controls/input.stories.ts",
                "deprecated": false,
                "deprecationMessage": "",
                "type": "Story",
                "defaultValue": "{\r\n  render: (args) => ({\r\n    props: args,\r\n    template: `<input soliasInput type=\"password\" placeholder=\"Enter password\" />`,\r\n  }),\r\n}"
            },
            {
                "name": "preview",
                "ctype": "miscellaneous",
                "subtype": "variable",
                "file": "projects/solias-components/.storybook/preview.ts",
                "deprecated": false,
                "deprecationMessage": "",
                "type": "Preview",
                "defaultValue": "{\r\n  parameters: {\r\n    controls: {\r\n      matchers: {\r\n        color: /(background|color)$/i,\r\n        date: /Date$/i,\r\n      },\r\n    },\r\n  },\r\n  decorators: [\r\n    withThemeByClassName({\r\n      themes: {\r\n        light: 'light', // No class applied for light theme\r\n        dark: 'dark', // Apply 'dark' class for dark theme\r\n      },\r\n      defaultTheme: 'light', // Default theme\r\n    }),\r\n  ],\r\n}"
            },
            {
                "name": "Primary",
                "ctype": "miscellaneous",
                "subtype": "variable",
                "file": "projects/solias-components/src/stories/buttons/button.stories.ts",
                "deprecated": false,
                "deprecationMessage": "",
                "type": "Story",
                "defaultValue": "{\n  args: {\n    variant: 'primary',\n  },\n}"
            },
            {
                "name": "Secondary",
                "ctype": "miscellaneous",
                "subtype": "variable",
                "file": "projects/solias-components/src/stories/buttons/button.stories.ts",
                "deprecated": false,
                "deprecationMessage": "",
                "type": "Story",
                "defaultValue": "{\n  args: {\n    variant: 'secondary',\n  },\n}"
            },
            {
                "name": "Select",
                "ctype": "miscellaneous",
                "subtype": "variable",
                "file": "projects/solias-components/src/stories/form-controls/select.stories.ts",
                "deprecated": false,
                "deprecationMessage": "",
                "type": "Story",
                "defaultValue": "{\r\n  render: (args) => ({\r\n    props: args,\r\n    template: `<select soliasSelect>\r\n        <option selected>Choose a country</option>\r\n        <option value=\"US\">Sri Lanka</option>\r\n        <option value=\"US\">United States</option>\r\n        <option value=\"CA\">Canada</option>\r\n        <option value=\"FR\">France</option>\r\n        <option value=\"DE\">Germany</option>\r\n    </select>`,\r\n  }),\r\n}"
            },
            {
                "name": "SelectDisabled",
                "ctype": "miscellaneous",
                "subtype": "variable",
                "file": "projects/solias-components/src/stories/form-controls/select.stories.ts",
                "deprecated": false,
                "deprecationMessage": "",
                "type": "Story",
                "defaultValue": "{\r\n    render: (args) => ({\r\n        props: args,\r\n        template: `<select soliasSelect [disabled]=\"true\">\r\n            <option selected>Choose a country</option>\r\n            <option value=\"US\">Sri Lanka</option>\r\n            <option value=\"US\">United States</option>\r\n            <option value=\"CA\">Canada</option>\r\n            <option value=\"FR\">France</option>\r\n            <option value=\"DE\">Germany</option>\r\n        </select>`,\r\n      }),\r\n}"
            },
            {
                "name": "Small",
                "ctype": "miscellaneous",
                "subtype": "variable",
                "file": "projects/solias-components/src/stories/buttons/button.stories.ts",
                "deprecated": false,
                "deprecationMessage": "",
                "type": "Story",
                "defaultValue": "{\n  args: {\n    variant: 'primary',\n    size: 'small',\n  },\n}"
            },
            {
                "name": "Success",
                "ctype": "miscellaneous",
                "subtype": "variable",
                "file": "projects/solias-components/src/stories/buttons/button.stories.ts",
                "deprecated": false,
                "deprecationMessage": "",
                "type": "Story",
                "defaultValue": "{\n  args: {\n    variant: 'success',\n  },\n}"
            },
            {
                "name": "Tertiary",
                "ctype": "miscellaneous",
                "subtype": "variable",
                "file": "projects/solias-components/src/stories/buttons/button.stories.ts",
                "deprecated": false,
                "deprecationMessage": "",
                "type": "Story",
                "defaultValue": "{\n  args: {\n    variant: 'tertiary',\n  },\n}"
            },
            {
                "name": "textarea",
                "ctype": "miscellaneous",
                "subtype": "variable",
                "file": "projects/solias-components/src/stories/form-controls/textarea.stories.ts",
                "deprecated": false,
                "deprecationMessage": "",
                "type": "Story",
                "defaultValue": "{\r\n  render: (args) => ({\r\n    props: args,\r\n    template: `<textarea soliasTextarea placeholder=\"Enter text\"></textarea>`,\r\n  }),\r\n}"
            },
            {
                "name": "textareaDisabled",
                "ctype": "miscellaneous",
                "subtype": "variable",
                "file": "projects/solias-components/src/stories/form-controls/textarea.stories.ts",
                "deprecated": false,
                "deprecationMessage": "",
                "type": "Story",
                "defaultValue": "{\r\n  render: (args) => ({\r\n    props: args,\r\n    template: `<textarea soliasTextarea [disabled]=\"true\">Disabled text</textarea>`,\r\n  }),\r\n}"
            },
            {
                "name": "textInput",
                "ctype": "miscellaneous",
                "subtype": "variable",
                "file": "projects/solias-components/src/stories/form-controls/input.stories.ts",
                "deprecated": false,
                "deprecationMessage": "",
                "type": "Story",
                "defaultValue": "{\r\n  render: (args) => ({\r\n    props: args,\r\n    template: `<input soliasInput type=\"text\" placeholder=\"Enter text\" />`,\r\n  }),\r\n}"
            }
        ],
        "functions": [],
        "typealiases": [
            {
                "name": "Story",
                "ctype": "miscellaneous",
                "subtype": "typealias",
                "rawtype": "StoryObj<SoliasButtonDirective>",
                "file": "projects/solias-components/src/stories/buttons/button.stories.ts",
                "deprecated": false,
                "deprecationMessage": "",
                "description": "",
                "kind": 183
            },
            {
                "name": "Story",
                "ctype": "miscellaneous",
                "subtype": "typealias",
                "rawtype": "StoryObj<SoliasCheckboxDirective>",
                "file": "projects/solias-components/src/stories/form-controls/checkbox.stories.ts",
                "deprecated": false,
                "deprecationMessage": "",
                "description": "",
                "kind": 183
            },
            {
                "name": "Story",
                "ctype": "miscellaneous",
                "subtype": "typealias",
                "rawtype": "StoryObj<SoliasInputDirective>",
                "file": "projects/solias-components/src/stories/form-controls/input.stories.ts",
                "deprecated": false,
                "deprecationMessage": "",
                "description": "",
                "kind": 183
            },
            {
                "name": "Story",
                "ctype": "miscellaneous",
                "subtype": "typealias",
                "rawtype": "StoryObj<SoliasRadioDirective>",
                "file": "projects/solias-components/src/stories/form-controls/radio.stories.ts",
                "deprecated": false,
                "deprecationMessage": "",
                "description": "",
                "kind": 183
            },
            {
                "name": "Story",
                "ctype": "miscellaneous",
                "subtype": "typealias",
                "rawtype": "StoryObj<SoliasRangeDirective>",
                "file": "projects/solias-components/src/stories/form-controls/range.stories.ts",
                "deprecated": false,
                "deprecationMessage": "",
                "description": "",
                "kind": 183
            },
            {
                "name": "Story",
                "ctype": "miscellaneous",
                "subtype": "typealias",
                "rawtype": "StoryObj<SoliasSelectDirective>",
                "file": "projects/solias-components/src/stories/form-controls/select.stories.ts",
                "deprecated": false,
                "deprecationMessage": "",
                "description": "",
                "kind": 183
            },
            {
                "name": "Story",
                "ctype": "miscellaneous",
                "subtype": "typealias",
                "rawtype": "StoryObj<SoliasTextareaDirective>",
                "file": "projects/solias-components/src/stories/form-controls/textarea.stories.ts",
                "deprecated": false,
                "deprecationMessage": "",
                "description": "",
                "kind": 183
            }
        ],
        "enumerations": [],
        "groupedVariables": {
            "projects/solias-components/src/stories/form-controls/checkbox.stories.ts": [
                {
                    "name": "Checked",
                    "ctype": "miscellaneous",
                    "subtype": "variable",
                    "file": "projects/solias-components/src/stories/form-controls/checkbox.stories.ts",
                    "deprecated": false,
                    "deprecationMessage": "",
                    "type": "Story",
                    "defaultValue": "{\r\n  render: (args) => ({\r\n    props: args,\r\n    template: `<input soliasCheckbox type=\"checkbox\" checked/>`,\r\n  }),\r\n}"
                },
                {
                    "name": "defaultState",
                    "ctype": "miscellaneous",
                    "subtype": "variable",
                    "file": "projects/solias-components/src/stories/form-controls/checkbox.stories.ts",
                    "deprecated": false,
                    "deprecationMessage": "",
                    "type": "Story",
                    "defaultValue": "{\r\n  render: (args) => ({\r\n    props: args,\r\n    template: `<input soliasCheckbox type=\"checkbox\" />`,\r\n  }),\r\n}"
                },
                {
                    "name": "DisabledChecked",
                    "ctype": "miscellaneous",
                    "subtype": "variable",
                    "file": "projects/solias-components/src/stories/form-controls/checkbox.stories.ts",
                    "deprecated": false,
                    "deprecationMessage": "",
                    "type": "Story",
                    "defaultValue": "{\r\n  render: (args) => ({\r\n    props: args,\r\n    template: `<input soliasCheckbox type=\"checkbox\" [disabled]=\"true\" />`,\r\n  }),\r\n}"
                },
                {
                    "name": "DisabledUnchecked",
                    "ctype": "miscellaneous",
                    "subtype": "variable",
                    "file": "projects/solias-components/src/stories/form-controls/checkbox.stories.ts",
                    "deprecated": false,
                    "deprecationMessage": "",
                    "type": "Story",
                    "defaultValue": "{\r\n  render: (args) => ({\r\n    props: args,\r\n    template: `<input soliasCheckbox type=\"checkbox\" [disabled]=\"true\" checked />`,\r\n  }),\r\n}"
                },
                {
                    "name": "meta",
                    "ctype": "miscellaneous",
                    "subtype": "variable",
                    "file": "projects/solias-components/src/stories/form-controls/checkbox.stories.ts",
                    "deprecated": false,
                    "deprecationMessage": "",
                    "type": "Meta<SoliasCheckboxDirective>",
                    "defaultValue": "{\r\n  title: 'Form Controls/Checkbox',\r\n  component: SoliasCheckboxDirective,\r\n  tags: ['autodocs']\r\n}"
                }
            ],
            "projects/solias-components/src/stories/form-controls/radio.stories.ts": [
                {
                    "name": "Checked",
                    "ctype": "miscellaneous",
                    "subtype": "variable",
                    "file": "projects/solias-components/src/stories/form-controls/radio.stories.ts",
                    "deprecated": false,
                    "deprecationMessage": "",
                    "type": "Story",
                    "defaultValue": "{\r\n  render: (args) => ({\r\n    props: args,\r\n    template: `<input soliasRadio type=\"radio\" checked />`,\r\n  }),\r\n}"
                },
                {
                    "name": "defaultState",
                    "ctype": "miscellaneous",
                    "subtype": "variable",
                    "file": "projects/solias-components/src/stories/form-controls/radio.stories.ts",
                    "deprecated": false,
                    "deprecationMessage": "",
                    "type": "Story",
                    "defaultValue": "{\r\n  render: (args) => ({\r\n    props: args,\r\n    template: `<input soliasRadio type=\"radio\" />`,\r\n  }),\r\n}"
                },
                {
                    "name": "DisabledChecked",
                    "ctype": "miscellaneous",
                    "subtype": "variable",
                    "file": "projects/solias-components/src/stories/form-controls/radio.stories.ts",
                    "deprecated": false,
                    "deprecationMessage": "",
                    "type": "Story",
                    "defaultValue": "{\r\n  render: (args) => ({\r\n    props: args,\r\n    template: `<input soliasRadio type=\"radio\" [disabled]=\"true\" />`,\r\n  }),\r\n}"
                },
                {
                    "name": "DisabledUnchecked",
                    "ctype": "miscellaneous",
                    "subtype": "variable",
                    "file": "projects/solias-components/src/stories/form-controls/radio.stories.ts",
                    "deprecated": false,
                    "deprecationMessage": "",
                    "type": "Story",
                    "defaultValue": "{\r\n  render: (args) => ({\r\n    props: args,\r\n    template: `<input soliasRadio type=\"radio\" [disabled]=\"true\" checked />`,\r\n  }),\r\n}"
                },
                {
                    "name": "meta",
                    "ctype": "miscellaneous",
                    "subtype": "variable",
                    "file": "projects/solias-components/src/stories/form-controls/radio.stories.ts",
                    "deprecated": false,
                    "deprecationMessage": "",
                    "type": "Meta<SoliasRadioDirective>",
                    "defaultValue": "{\r\n  title: 'Form Controls/Radio',\r\n  component: SoliasRadioDirective,\r\n  tags: ['autodocs'],\r\n}"
                }
            ],
            "projects/solias-components/src/stories/form-controls/range.stories.ts": [
                {
                    "name": "defaultState",
                    "ctype": "miscellaneous",
                    "subtype": "variable",
                    "file": "projects/solias-components/src/stories/form-controls/range.stories.ts",
                    "deprecated": false,
                    "deprecationMessage": "",
                    "type": "Story",
                    "defaultValue": "{\r\n  render: (args) => ({\r\n    props: args,\r\n    template: `<input soliasRange type=\"range\" />`,\r\n  }),\r\n}"
                },
                {
                    "name": "disabledState",
                    "ctype": "miscellaneous",
                    "subtype": "variable",
                    "file": "projects/solias-components/src/stories/form-controls/range.stories.ts",
                    "deprecated": false,
                    "deprecationMessage": "",
                    "type": "Story",
                    "defaultValue": "{\r\n  render: (args) => ({\r\n    props: args,\r\n    template: `<input soliasRange type=\"range\" [disabled]=\"true\" />`,\r\n  }),\r\n}"
                },
                {
                    "name": "meta",
                    "ctype": "miscellaneous",
                    "subtype": "variable",
                    "file": "projects/solias-components/src/stories/form-controls/range.stories.ts",
                    "deprecated": false,
                    "deprecationMessage": "",
                    "type": "Meta<SoliasRangeDirective>",
                    "defaultValue": "{\r\n  title: 'Form Controls/Range',\r\n  component: SoliasRangeDirective,\r\n  tags: ['autodocs']\r\n}"
                }
            ],
            "projects/solias-components/src/stories/buttons/button.stories.ts": [
                {
                    "name": "Disabled",
                    "ctype": "miscellaneous",
                    "subtype": "variable",
                    "file": "projects/solias-components/src/stories/buttons/button.stories.ts",
                    "deprecated": false,
                    "deprecationMessage": "",
                    "type": "Story",
                    "defaultValue": "{\n  args: {\n    variant: 'primary',\n    disabled: true,\n  },\n}"
                },
                {
                    "name": "Error",
                    "ctype": "miscellaneous",
                    "subtype": "variable",
                    "file": "projects/solias-components/src/stories/buttons/button.stories.ts",
                    "deprecated": false,
                    "deprecationMessage": "",
                    "type": "Story",
                    "defaultValue": "{\n  args: {\n    variant: 'error',\n  },\n}"
                },
                {
                    "name": "Large",
                    "ctype": "miscellaneous",
                    "subtype": "variable",
                    "file": "projects/solias-components/src/stories/buttons/button.stories.ts",
                    "deprecated": false,
                    "deprecationMessage": "",
                    "type": "Story",
                    "defaultValue": "{\n  args: {\n    variant: 'primary',\n    size: 'large',\n  },\n}"
                },
                {
                    "name": "meta",
                    "ctype": "miscellaneous",
                    "subtype": "variable",
                    "file": "projects/solias-components/src/stories/buttons/button.stories.ts",
                    "deprecated": false,
                    "deprecationMessage": "",
                    "type": "Meta<SoliasButtonDirective>",
                    "defaultValue": "{\n  title: 'Buttons/Button',\n  component: SoliasButtonDirective,\n  tags: ['autodocs'],\n  argTypes: {\n    variant: {\n      control: 'select',\n      options: ['primary', 'secondary', 'tertiary', 'success', 'error'],\n      table: { defaultValue: { summary: 'primary' } },\n    },\n    size: {\n      control: 'select',\n      options: ['small', 'medium', 'large'],\n      table: { defaultValue: { summary: 'medium' } },\n    },\n    outlined: {\n      control: 'boolean',\n      table: { defaultValue: { summary: 'false' } },\n    },\n    disabled: {\n      control: 'boolean',\n      table: { defaultValue: { summary: 'false' } },\n    },\n  },\n  render: (args) => ({\n    props: args,\n    template: `<button soliasButton [variant]=\"variant\" [size]=\"size\" [outlined]=\"outlined\" [disabled]=\"disabled\">Button</button>`,\n  }),\n}"
                },
                {
                    "name": "Outlined",
                    "ctype": "miscellaneous",
                    "subtype": "variable",
                    "file": "projects/solias-components/src/stories/buttons/button.stories.ts",
                    "deprecated": false,
                    "deprecationMessage": "",
                    "type": "Story",
                    "defaultValue": "{\n  args: {\n    variant: 'primary',\n    outlined: true,\n  },\n}"
                },
                {
                    "name": "Primary",
                    "ctype": "miscellaneous",
                    "subtype": "variable",
                    "file": "projects/solias-components/src/stories/buttons/button.stories.ts",
                    "deprecated": false,
                    "deprecationMessage": "",
                    "type": "Story",
                    "defaultValue": "{\n  args: {\n    variant: 'primary',\n  },\n}"
                },
                {
                    "name": "Secondary",
                    "ctype": "miscellaneous",
                    "subtype": "variable",
                    "file": "projects/solias-components/src/stories/buttons/button.stories.ts",
                    "deprecated": false,
                    "deprecationMessage": "",
                    "type": "Story",
                    "defaultValue": "{\n  args: {\n    variant: 'secondary',\n  },\n}"
                },
                {
                    "name": "Small",
                    "ctype": "miscellaneous",
                    "subtype": "variable",
                    "file": "projects/solias-components/src/stories/buttons/button.stories.ts",
                    "deprecated": false,
                    "deprecationMessage": "",
                    "type": "Story",
                    "defaultValue": "{\n  args: {\n    variant: 'primary',\n    size: 'small',\n  },\n}"
                },
                {
                    "name": "Success",
                    "ctype": "miscellaneous",
                    "subtype": "variable",
                    "file": "projects/solias-components/src/stories/buttons/button.stories.ts",
                    "deprecated": false,
                    "deprecationMessage": "",
                    "type": "Story",
                    "defaultValue": "{\n  args: {\n    variant: 'success',\n  },\n}"
                },
                {
                    "name": "Tertiary",
                    "ctype": "miscellaneous",
                    "subtype": "variable",
                    "file": "projects/solias-components/src/stories/buttons/button.stories.ts",
                    "deprecated": false,
                    "deprecationMessage": "",
                    "type": "Story",
                    "defaultValue": "{\n  args: {\n    variant: 'tertiary',\n  },\n}"
                }
            ],
            "projects/solias-components/src/stories/form-controls/input.stories.ts": [
                {
                    "name": "inputDisabledState",
                    "ctype": "miscellaneous",
                    "subtype": "variable",
                    "file": "projects/solias-components/src/stories/form-controls/input.stories.ts",
                    "deprecated": false,
                    "deprecationMessage": "",
                    "type": "Story",
                    "defaultValue": "{\r\n  render: (args) => ({\r\n    props: args,\r\n    template: `<input soliasInput type=\"text\" [disabled]=\"true\" [value]=\"'Disabled value'\" />`,\r\n  }),\r\n}"
                },
                {
                    "name": "inputInvalidState",
                    "ctype": "miscellaneous",
                    "subtype": "variable",
                    "file": "projects/solias-components/src/stories/form-controls/input.stories.ts",
                    "deprecated": false,
                    "deprecationMessage": "",
                    "type": "Story",
                    "defaultValue": "{\r\n  render: (args) => ({\r\n    props: args,\r\n    template: `<input soliasInput type=\"text\" [validity]=\"'invalid'\" [value]=\"'Invalid value'\" />`,\r\n  }),\r\n}"
                },
                {
                    "name": "inputReadonlyState",
                    "ctype": "miscellaneous",
                    "subtype": "variable",
                    "file": "projects/solias-components/src/stories/form-controls/input.stories.ts",
                    "deprecated": false,
                    "deprecationMessage": "",
                    "type": "Story",
                    "defaultValue": "{\r\n  render: (args) => ({\r\n    props: args,\r\n    template: `<input soliasInput type=\"text\" [readOnly]=\"true\" [value]=\"'Readonly value'\" />`,\r\n  }),\r\n}"
                },
                {
                    "name": "inputValidState",
                    "ctype": "miscellaneous",
                    "subtype": "variable",
                    "file": "projects/solias-components/src/stories/form-controls/input.stories.ts",
                    "deprecated": false,
                    "deprecationMessage": "",
                    "type": "Story",
                    "defaultValue": "{\r\n  render: (args) => ({\r\n    props: args,\r\n    template: `<input soliasInput type=\"text\" [validity]=\"'valid'\" [value]=\"'Valid value'\" />`,\r\n  }),\r\n}"
                },
                {
                    "name": "meta",
                    "ctype": "miscellaneous",
                    "subtype": "variable",
                    "file": "projects/solias-components/src/stories/form-controls/input.stories.ts",
                    "deprecated": false,
                    "deprecationMessage": "",
                    "type": "Meta<SoliasInputDirective>",
                    "defaultValue": "{\r\n  component: SoliasInputDirective,\r\n  title: 'Form Controls/Inputs',\r\n  tags: ['autodocs'],\r\n}"
                },
                {
                    "name": "numberInput",
                    "ctype": "miscellaneous",
                    "subtype": "variable",
                    "file": "projects/solias-components/src/stories/form-controls/input.stories.ts",
                    "deprecated": false,
                    "deprecationMessage": "",
                    "type": "Story",
                    "defaultValue": "{\r\n  render: (args) => ({\r\n    props: args,\r\n    template: `<input soliasInput type=\"number\" placeholder=\"Enter number\" />`,\r\n  }),\r\n}"
                },
                {
                    "name": "passwordInput",
                    "ctype": "miscellaneous",
                    "subtype": "variable",
                    "file": "projects/solias-components/src/stories/form-controls/input.stories.ts",
                    "deprecated": false,
                    "deprecationMessage": "",
                    "type": "Story",
                    "defaultValue": "{\r\n  render: (args) => ({\r\n    props: args,\r\n    template: `<input soliasInput type=\"password\" placeholder=\"Enter password\" />`,\r\n  }),\r\n}"
                },
                {
                    "name": "textInput",
                    "ctype": "miscellaneous",
                    "subtype": "variable",
                    "file": "projects/solias-components/src/stories/form-controls/input.stories.ts",
                    "deprecated": false,
                    "deprecationMessage": "",
                    "type": "Story",
                    "defaultValue": "{\r\n  render: (args) => ({\r\n    props: args,\r\n    template: `<input soliasInput type=\"text\" placeholder=\"Enter text\" />`,\r\n  }),\r\n}"
                }
            ],
            "projects/solias-components/src/stories/form-controls/select.stories.ts": [
                {
                    "name": "meta",
                    "ctype": "miscellaneous",
                    "subtype": "variable",
                    "file": "projects/solias-components/src/stories/form-controls/select.stories.ts",
                    "deprecated": false,
                    "deprecationMessage": "",
                    "type": "Meta<SoliasSelectDirective>",
                    "defaultValue": "{\r\n  component: SoliasSelectDirective,\r\n  title: 'Form Controls/Select',\r\n  tags: ['autodocs'],\r\n}"
                },
                {
                    "name": "Select",
                    "ctype": "miscellaneous",
                    "subtype": "variable",
                    "file": "projects/solias-components/src/stories/form-controls/select.stories.ts",
                    "deprecated": false,
                    "deprecationMessage": "",
                    "type": "Story",
                    "defaultValue": "{\r\n  render: (args) => ({\r\n    props: args,\r\n    template: `<select soliasSelect>\r\n        <option selected>Choose a country</option>\r\n        <option value=\"US\">Sri Lanka</option>\r\n        <option value=\"US\">United States</option>\r\n        <option value=\"CA\">Canada</option>\r\n        <option value=\"FR\">France</option>\r\n        <option value=\"DE\">Germany</option>\r\n    </select>`,\r\n  }),\r\n}"
                },
                {
                    "name": "SelectDisabled",
                    "ctype": "miscellaneous",
                    "subtype": "variable",
                    "file": "projects/solias-components/src/stories/form-controls/select.stories.ts",
                    "deprecated": false,
                    "deprecationMessage": "",
                    "type": "Story",
                    "defaultValue": "{\r\n    render: (args) => ({\r\n        props: args,\r\n        template: `<select soliasSelect [disabled]=\"true\">\r\n            <option selected>Choose a country</option>\r\n            <option value=\"US\">Sri Lanka</option>\r\n            <option value=\"US\">United States</option>\r\n            <option value=\"CA\">Canada</option>\r\n            <option value=\"FR\">France</option>\r\n            <option value=\"DE\">Germany</option>\r\n        </select>`,\r\n      }),\r\n}"
                }
            ],
            "projects/solias-components/src/stories/form-controls/textarea.stories.ts": [
                {
                    "name": "meta",
                    "ctype": "miscellaneous",
                    "subtype": "variable",
                    "file": "projects/solias-components/src/stories/form-controls/textarea.stories.ts",
                    "deprecated": false,
                    "deprecationMessage": "",
                    "type": "Meta<SoliasTextareaDirective>",
                    "defaultValue": "{\r\n  component: SoliasTextareaDirective,\r\n  title: 'Form Controls/Textarea',\r\n  tags: ['autodocs'],\r\n}"
                },
                {
                    "name": "textarea",
                    "ctype": "miscellaneous",
                    "subtype": "variable",
                    "file": "projects/solias-components/src/stories/form-controls/textarea.stories.ts",
                    "deprecated": false,
                    "deprecationMessage": "",
                    "type": "Story",
                    "defaultValue": "{\r\n  render: (args) => ({\r\n    props: args,\r\n    template: `<textarea soliasTextarea placeholder=\"Enter text\"></textarea>`,\r\n  }),\r\n}"
                },
                {
                    "name": "textareaDisabled",
                    "ctype": "miscellaneous",
                    "subtype": "variable",
                    "file": "projects/solias-components/src/stories/form-controls/textarea.stories.ts",
                    "deprecated": false,
                    "deprecationMessage": "",
                    "type": "Story",
                    "defaultValue": "{\r\n  render: (args) => ({\r\n    props: args,\r\n    template: `<textarea soliasTextarea [disabled]=\"true\">Disabled text</textarea>`,\r\n  }),\r\n}"
                }
            ],
            "projects/solias-components/.storybook/preview.ts": [
                {
                    "name": "preview",
                    "ctype": "miscellaneous",
                    "subtype": "variable",
                    "file": "projects/solias-components/.storybook/preview.ts",
                    "deprecated": false,
                    "deprecationMessage": "",
                    "type": "Preview",
                    "defaultValue": "{\r\n  parameters: {\r\n    controls: {\r\n      matchers: {\r\n        color: /(background|color)$/i,\r\n        date: /Date$/i,\r\n      },\r\n    },\r\n  },\r\n  decorators: [\r\n    withThemeByClassName({\r\n      themes: {\r\n        light: 'light', // No class applied for light theme\r\n        dark: 'dark', // Apply 'dark' class for dark theme\r\n      },\r\n      defaultTheme: 'light', // Default theme\r\n    }),\r\n  ],\r\n}"
                }
            ]
        },
        "groupedFunctions": {},
        "groupedEnumerations": {},
        "groupedTypeAliases": {
            "projects/solias-components/src/stories/buttons/button.stories.ts": [
                {
                    "name": "Story",
                    "ctype": "miscellaneous",
                    "subtype": "typealias",
                    "rawtype": "StoryObj<SoliasButtonDirective>",
                    "file": "projects/solias-components/src/stories/buttons/button.stories.ts",
                    "deprecated": false,
                    "deprecationMessage": "",
                    "description": "",
                    "kind": 183
                }
            ],
            "projects/solias-components/src/stories/form-controls/checkbox.stories.ts": [
                {
                    "name": "Story",
                    "ctype": "miscellaneous",
                    "subtype": "typealias",
                    "rawtype": "StoryObj<SoliasCheckboxDirective>",
                    "file": "projects/solias-components/src/stories/form-controls/checkbox.stories.ts",
                    "deprecated": false,
                    "deprecationMessage": "",
                    "description": "",
                    "kind": 183
                }
            ],
            "projects/solias-components/src/stories/form-controls/input.stories.ts": [
                {
                    "name": "Story",
                    "ctype": "miscellaneous",
                    "subtype": "typealias",
                    "rawtype": "StoryObj<SoliasInputDirective>",
                    "file": "projects/solias-components/src/stories/form-controls/input.stories.ts",
                    "deprecated": false,
                    "deprecationMessage": "",
                    "description": "",
                    "kind": 183
                }
            ],
            "projects/solias-components/src/stories/form-controls/radio.stories.ts": [
                {
                    "name": "Story",
                    "ctype": "miscellaneous",
                    "subtype": "typealias",
                    "rawtype": "StoryObj<SoliasRadioDirective>",
                    "file": "projects/solias-components/src/stories/form-controls/radio.stories.ts",
                    "deprecated": false,
                    "deprecationMessage": "",
                    "description": "",
                    "kind": 183
                }
            ],
            "projects/solias-components/src/stories/form-controls/range.stories.ts": [
                {
                    "name": "Story",
                    "ctype": "miscellaneous",
                    "subtype": "typealias",
                    "rawtype": "StoryObj<SoliasRangeDirective>",
                    "file": "projects/solias-components/src/stories/form-controls/range.stories.ts",
                    "deprecated": false,
                    "deprecationMessage": "",
                    "description": "",
                    "kind": 183
                }
            ],
            "projects/solias-components/src/stories/form-controls/select.stories.ts": [
                {
                    "name": "Story",
                    "ctype": "miscellaneous",
                    "subtype": "typealias",
                    "rawtype": "StoryObj<SoliasSelectDirective>",
                    "file": "projects/solias-components/src/stories/form-controls/select.stories.ts",
                    "deprecated": false,
                    "deprecationMessage": "",
                    "description": "",
                    "kind": 183
                }
            ],
            "projects/solias-components/src/stories/form-controls/textarea.stories.ts": [
                {
                    "name": "Story",
                    "ctype": "miscellaneous",
                    "subtype": "typealias",
                    "rawtype": "StoryObj<SoliasTextareaDirective>",
                    "file": "projects/solias-components/src/stories/form-controls/textarea.stories.ts",
                    "deprecated": false,
                    "deprecationMessage": "",
                    "description": "",
                    "kind": 183
                }
            ]
        }
    },
    "routes": [],
    "coverage": {
        "count": 0,
        "status": "low",
        "files": [
            {
                "filePath": "projects/solias-components/.storybook/preview.ts",
                "type": "variable",
                "linktype": "miscellaneous",
                "linksubtype": "variable",
                "name": "preview",
                "coveragePercent": 0,
                "coverageCount": "0/1",
                "status": "low"
            },
            {
                "filePath": "projects/solias-components/src/stories/buttons/button.stories.ts",
                "type": "variable",
                "linktype": "miscellaneous",
                "linksubtype": "variable",
                "name": "Disabled",
                "coveragePercent": 0,
                "coverageCount": "0/1",
                "status": "low"
            },
            {
                "filePath": "projects/solias-components/src/stories/buttons/button.stories.ts",
                "type": "variable",
                "linktype": "miscellaneous",
                "linksubtype": "variable",
                "name": "Error",
                "coveragePercent": 0,
                "coverageCount": "0/1",
                "status": "low"
            },
            {
                "filePath": "projects/solias-components/src/stories/buttons/button.stories.ts",
                "type": "variable",
                "linktype": "miscellaneous",
                "linksubtype": "variable",
                "name": "Large",
                "coveragePercent": 0,
                "coverageCount": "0/1",
                "status": "low"
            },
            {
                "filePath": "projects/solias-components/src/stories/buttons/button.stories.ts",
                "type": "variable",
                "linktype": "miscellaneous",
                "linksubtype": "variable",
                "name": "meta",
                "coveragePercent": 0,
                "coverageCount": "0/1",
                "status": "low"
            },
            {
                "filePath": "projects/solias-components/src/stories/buttons/button.stories.ts",
                "type": "variable",
                "linktype": "miscellaneous",
                "linksubtype": "variable",
                "name": "Outlined",
                "coveragePercent": 0,
                "coverageCount": "0/1",
                "status": "low"
            },
            {
                "filePath": "projects/solias-components/src/stories/buttons/button.stories.ts",
                "type": "variable",
                "linktype": "miscellaneous",
                "linksubtype": "variable",
                "name": "Primary",
                "coveragePercent": 0,
                "coverageCount": "0/1",
                "status": "low"
            },
            {
                "filePath": "projects/solias-components/src/stories/buttons/button.stories.ts",
                "type": "variable",
                "linktype": "miscellaneous",
                "linksubtype": "variable",
                "name": "Secondary",
                "coveragePercent": 0,
                "coverageCount": "0/1",
                "status": "low"
            },
            {
                "filePath": "projects/solias-components/src/stories/buttons/button.stories.ts",
                "type": "variable",
                "linktype": "miscellaneous",
                "linksubtype": "variable",
                "name": "Small",
                "coveragePercent": 0,
                "coverageCount": "0/1",
                "status": "low"
            },
            {
                "filePath": "projects/solias-components/src/stories/buttons/button.stories.ts",
                "type": "variable",
                "linktype": "miscellaneous",
                "linksubtype": "variable",
                "name": "Success",
                "coveragePercent": 0,
                "coverageCount": "0/1",
                "status": "low"
            },
            {
                "filePath": "projects/solias-components/src/stories/buttons/button.stories.ts",
                "type": "variable",
                "linktype": "miscellaneous",
                "linksubtype": "variable",
                "name": "Tertiary",
                "coveragePercent": 0,
                "coverageCount": "0/1",
                "status": "low"
            },
            {
                "filePath": "projects/solias-components/src/stories/buttons/button.stories.ts",
                "type": "type alias",
                "linktype": "miscellaneous",
                "linksubtype": "typealias",
                "name": "Story",
                "coveragePercent": 0,
                "coverageCount": "0/1",
                "status": "low"
            },
            {
                "filePath": "projects/solias-components/src/stories/form-controls/checkbox.stories.ts",
                "type": "variable",
                "linktype": "miscellaneous",
                "linksubtype": "variable",
                "name": "Checked",
                "coveragePercent": 0,
                "coverageCount": "0/1",
                "status": "low"
            },
            {
                "filePath": "projects/solias-components/src/stories/form-controls/checkbox.stories.ts",
                "type": "variable",
                "linktype": "miscellaneous",
                "linksubtype": "variable",
                "name": "defaultState",
                "coveragePercent": 0,
                "coverageCount": "0/1",
                "status": "low"
            },
            {
                "filePath": "projects/solias-components/src/stories/form-controls/checkbox.stories.ts",
                "type": "variable",
                "linktype": "miscellaneous",
                "linksubtype": "variable",
                "name": "DisabledChecked",
                "coveragePercent": 0,
                "coverageCount": "0/1",
                "status": "low"
            },
            {
                "filePath": "projects/solias-components/src/stories/form-controls/checkbox.stories.ts",
                "type": "variable",
                "linktype": "miscellaneous",
                "linksubtype": "variable",
                "name": "DisabledUnchecked",
                "coveragePercent": 0,
                "coverageCount": "0/1",
                "status": "low"
            },
            {
                "filePath": "projects/solias-components/src/stories/form-controls/checkbox.stories.ts",
                "type": "variable",
                "linktype": "miscellaneous",
                "linksubtype": "variable",
                "name": "meta",
                "coveragePercent": 0,
                "coverageCount": "0/1",
                "status": "low"
            },
            {
                "filePath": "projects/solias-components/src/stories/form-controls/checkbox.stories.ts",
                "type": "type alias",
                "linktype": "miscellaneous",
                "linksubtype": "typealias",
                "name": "Story",
                "coveragePercent": 0,
                "coverageCount": "0/1",
                "status": "low"
            },
            {
                "filePath": "projects/solias-components/src/stories/form-controls/input.stories.ts",
                "type": "variable",
                "linktype": "miscellaneous",
                "linksubtype": "variable",
                "name": "inputDisabledState",
                "coveragePercent": 0,
                "coverageCount": "0/1",
                "status": "low"
            },
            {
                "filePath": "projects/solias-components/src/stories/form-controls/input.stories.ts",
                "type": "variable",
                "linktype": "miscellaneous",
                "linksubtype": "variable",
                "name": "inputInvalidState",
                "coveragePercent": 0,
                "coverageCount": "0/1",
                "status": "low"
            },
            {
                "filePath": "projects/solias-components/src/stories/form-controls/input.stories.ts",
                "type": "variable",
                "linktype": "miscellaneous",
                "linksubtype": "variable",
                "name": "inputReadonlyState",
                "coveragePercent": 0,
                "coverageCount": "0/1",
                "status": "low"
            },
            {
                "filePath": "projects/solias-components/src/stories/form-controls/input.stories.ts",
                "type": "variable",
                "linktype": "miscellaneous",
                "linksubtype": "variable",
                "name": "inputValidState",
                "coveragePercent": 0,
                "coverageCount": "0/1",
                "status": "low"
            },
            {
                "filePath": "projects/solias-components/src/stories/form-controls/input.stories.ts",
                "type": "variable",
                "linktype": "miscellaneous",
                "linksubtype": "variable",
                "name": "meta",
                "coveragePercent": 0,
                "coverageCount": "0/1",
                "status": "low"
            },
            {
                "filePath": "projects/solias-components/src/stories/form-controls/input.stories.ts",
                "type": "variable",
                "linktype": "miscellaneous",
                "linksubtype": "variable",
                "name": "numberInput",
                "coveragePercent": 0,
                "coverageCount": "0/1",
                "status": "low"
            },
            {
                "filePath": "projects/solias-components/src/stories/form-controls/input.stories.ts",
                "type": "variable",
                "linktype": "miscellaneous",
                "linksubtype": "variable",
                "name": "passwordInput",
                "coveragePercent": 0,
                "coverageCount": "0/1",
                "status": "low"
            },
            {
                "filePath": "projects/solias-components/src/stories/form-controls/input.stories.ts",
                "type": "variable",
                "linktype": "miscellaneous",
                "linksubtype": "variable",
                "name": "textInput",
                "coveragePercent": 0,
                "coverageCount": "0/1",
                "status": "low"
            },
            {
                "filePath": "projects/solias-components/src/stories/form-controls/input.stories.ts",
                "type": "type alias",
                "linktype": "miscellaneous",
                "linksubtype": "typealias",
                "name": "Story",
                "coveragePercent": 0,
                "coverageCount": "0/1",
                "status": "low"
            },
            {
                "filePath": "projects/solias-components/src/stories/form-controls/radio.stories.ts",
                "type": "variable",
                "linktype": "miscellaneous",
                "linksubtype": "variable",
                "name": "Checked",
                "coveragePercent": 0,
                "coverageCount": "0/1",
                "status": "low"
            },
            {
                "filePath": "projects/solias-components/src/stories/form-controls/radio.stories.ts",
                "type": "variable",
                "linktype": "miscellaneous",
                "linksubtype": "variable",
                "name": "defaultState",
                "coveragePercent": 0,
                "coverageCount": "0/1",
                "status": "low"
            },
            {
                "filePath": "projects/solias-components/src/stories/form-controls/radio.stories.ts",
                "type": "variable",
                "linktype": "miscellaneous",
                "linksubtype": "variable",
                "name": "DisabledChecked",
                "coveragePercent": 0,
                "coverageCount": "0/1",
                "status": "low"
            },
            {
                "filePath": "projects/solias-components/src/stories/form-controls/radio.stories.ts",
                "type": "variable",
                "linktype": "miscellaneous",
                "linksubtype": "variable",
                "name": "DisabledUnchecked",
                "coveragePercent": 0,
                "coverageCount": "0/1",
                "status": "low"
            },
            {
                "filePath": "projects/solias-components/src/stories/form-controls/radio.stories.ts",
                "type": "variable",
                "linktype": "miscellaneous",
                "linksubtype": "variable",
                "name": "meta",
                "coveragePercent": 0,
                "coverageCount": "0/1",
                "status": "low"
            },
            {
                "filePath": "projects/solias-components/src/stories/form-controls/radio.stories.ts",
                "type": "type alias",
                "linktype": "miscellaneous",
                "linksubtype": "typealias",
                "name": "Story",
                "coveragePercent": 0,
                "coverageCount": "0/1",
                "status": "low"
            },
            {
                "filePath": "projects/solias-components/src/stories/form-controls/range.stories.ts",
                "type": "variable",
                "linktype": "miscellaneous",
                "linksubtype": "variable",
                "name": "defaultState",
                "coveragePercent": 0,
                "coverageCount": "0/1",
                "status": "low"
            },
            {
                "filePath": "projects/solias-components/src/stories/form-controls/range.stories.ts",
                "type": "variable",
                "linktype": "miscellaneous",
                "linksubtype": "variable",
                "name": "disabledState",
                "coveragePercent": 0,
                "coverageCount": "0/1",
                "status": "low"
            },
            {
                "filePath": "projects/solias-components/src/stories/form-controls/range.stories.ts",
                "type": "variable",
                "linktype": "miscellaneous",
                "linksubtype": "variable",
                "name": "meta",
                "coveragePercent": 0,
                "coverageCount": "0/1",
                "status": "low"
            },
            {
                "filePath": "projects/solias-components/src/stories/form-controls/range.stories.ts",
                "type": "type alias",
                "linktype": "miscellaneous",
                "linksubtype": "typealias",
                "name": "Story",
                "coveragePercent": 0,
                "coverageCount": "0/1",
                "status": "low"
            },
            {
                "filePath": "projects/solias-components/src/stories/form-controls/select.stories.ts",
                "type": "variable",
                "linktype": "miscellaneous",
                "linksubtype": "variable",
                "name": "meta",
                "coveragePercent": 0,
                "coverageCount": "0/1",
                "status": "low"
            },
            {
                "filePath": "projects/solias-components/src/stories/form-controls/select.stories.ts",
                "type": "variable",
                "linktype": "miscellaneous",
                "linksubtype": "variable",
                "name": "Select",
                "coveragePercent": 0,
                "coverageCount": "0/1",
                "status": "low"
            },
            {
                "filePath": "projects/solias-components/src/stories/form-controls/select.stories.ts",
                "type": "variable",
                "linktype": "miscellaneous",
                "linksubtype": "variable",
                "name": "SelectDisabled",
                "coveragePercent": 0,
                "coverageCount": "0/1",
                "status": "low"
            },
            {
                "filePath": "projects/solias-components/src/stories/form-controls/select.stories.ts",
                "type": "type alias",
                "linktype": "miscellaneous",
                "linksubtype": "typealias",
                "name": "Story",
                "coveragePercent": 0,
                "coverageCount": "0/1",
                "status": "low"
            },
            {
                "filePath": "projects/solias-components/src/stories/form-controls/textarea.stories.ts",
                "type": "variable",
                "linktype": "miscellaneous",
                "linksubtype": "variable",
                "name": "meta",
                "coveragePercent": 0,
                "coverageCount": "0/1",
                "status": "low"
            },
            {
                "filePath": "projects/solias-components/src/stories/form-controls/textarea.stories.ts",
                "type": "variable",
                "linktype": "miscellaneous",
                "linksubtype": "variable",
                "name": "textarea",
                "coveragePercent": 0,
                "coverageCount": "0/1",
                "status": "low"
            },
            {
                "filePath": "projects/solias-components/src/stories/form-controls/textarea.stories.ts",
                "type": "variable",
                "linktype": "miscellaneous",
                "linksubtype": "variable",
                "name": "textareaDisabled",
                "coveragePercent": 0,
                "coverageCount": "0/1",
                "status": "low"
            },
            {
                "filePath": "projects/solias-components/src/stories/form-controls/textarea.stories.ts",
                "type": "type alias",
                "linktype": "miscellaneous",
                "linksubtype": "typealias",
                "name": "Story",
                "coveragePercent": 0,
                "coverageCount": "0/1",
                "status": "low"
            }
        ]
    }
}